gldpy/__init__.py
gldpy/_gld_module.py
gldpy-0.2.dist-info/LICENSE
gldpy-0.2.dist-info/METADATA
gldpy-0.2.dist-info/WHEEL
gldpy-0.2.dist-info/top_level.txt
gldpy-0.2.dist-info/RECORD
