Metadata-Version: 2.1
Name: gldpy
Version: 0.2
Summary: Generalized Lambda Distribution for Python
Home-page: https://github.com/alexsandi/gldpy
Author: Aleksandra Alekseeva
Author-email: alex_sandi@mail.ru
License: MIT
Platform: UNKNOWN
Classifier: Programming Language :: Python :: 3
Classifier: License :: OSI Approved :: MIT License
